hdh/__init__.py
hdh/converters/__init__.py
hdh/converters/braket_converter.py
hdh/converters/cirq_converter.py
hdh/converters/pennylane_converter.py
hdh/converters/qasm_converter.py
hdh/converters/qiskit_converter.py
hdh/graph.py
hdh/hdh.py
hdh/models/__init__.py
hdh/models/circuit.py
hdh/models/mbqc.py
hdh/models/qca.py
hdh/models/qw.py
hdh/passes/README.md
hdh/passes/__init__.py
hdh/passes/cut.py
hdh/passes/primitives.py
hdh/visualize.py
hdh-0.2.8.dist-info/METADATA
hdh-0.2.8.dist-info/WHEEL
hdh-0.2.8.dist-info/licenses/LICENSE
hdh-0.2.8.dist-info/RECORD
