Metadata-Version: 2.4
Name: hdh
Version: 0.2.8
Summary: Hybrid Dependency Hypergraphs for quantum computation: translation, visualization, and partitioning.
License: MIT
License-File: LICENSE
Keywords: quantum,compiler,partitioning,hdh,hypergraph
Author: Maria Gragera Garces
Author-email: m.gragera.gaces@gmail.com
Requires-Python: >=3.10,<4.0
Classifier: License :: OSI Approved :: MIT License
Classifier: Programming Language :: Python :: 3
Classifier: Programming Language :: Python :: 3.10
Classifier: Programming Language :: Python :: 3.11
Classifier: Programming Language :: Python :: 3.12
Classifier: Programming Language :: Python :: 3.13
Classifier: Programming Language :: Python :: 3.14
Requires-Dist: matplotlib (>=3.0,<4.0)
Requires-Dist: metis (==0.2a5)
Requires-Dist: networkx (>=3.0,<4.0)
Requires-Dist: qiskit (>=1.0,<2.0)
Project-URL: Homepage, https://pypi.org/project/hdh/
Project-URL: Repository, https://github.com/grageragarces/hdh
